pyagadir/__init__.py
pyagadir/models.py
pyagadir/data/table2.csv
pyagadir/data/table3a.csv
pyagadir/data/table3b.csv
pyagadir/data/table4a.csv
pyagadir/data/table4b.csv
pyagadir-1.0.0.dist-info/LICENSE
pyagadir-1.0.0.dist-info/METADATA
pyagadir-1.0.0.dist-info/WHEEL
pyagadir-1.0.0.dist-info/top_level.txt
pyagadir-1.0.0.dist-info/zip-safe
pyagadir-1.0.0.dist-info/RECORD
