Metadata-Version: 2.1
Name: pyagadir
Version: 1.0.0
Summary: A model of alpha-helical stability based on statistical mechanics.
Home-page: https://github.com/reisalex/AGADIR
Author: Alexander Reis
Author-email: alex.camp.reis@gmail.com
License: "MIT"
Keywords: alpha-helix,biophysics,statistical mechanics,agadir,model
Classifier: License :: OSI Approved :: MIT License
Classifier: Programming Language :: Python :: 3
Requires-Python: <4,>=3.10
License-File: LICENSE
Requires-Dist: numpy (>=1.24.1)
Requires-Dist: pandas (>=1.5.2)
